<document xml:lang="nob" id="no_id"><header><title>Lesetips og boktips - Sametinget</title><genre code="admin"/><author><unknown/></author><year>2021</year><wordcount>194</wordcount><conversion_status type="standard"/><availability><free/></availability><multilingual/><origFileName>https://sametinget.no/saemiedigkien-garjagaetie/lohkh-munnjien-giele-voestesiereste/lohkemen-bijre-lohkede-ektesne/?sprak=1</origFileName><parallel_text xml:lang="sma" location="lohkemen_bijre_-_lohkede_ektesne.html"/><parallel_text xml:lang="sme" location="lohkama_birra_-_loga_ovttas.html"/><parallel_text xml:lang="smj" location="lahkama_birra_-_lahkit_aktan.html"/><metadata><uncomplete/></metadata><version>XSLtemplate $Revision$; file-specific xsl  Revision; common.xsl  $Revision$; </version></header><body><p type="title">Lesetips og boktips</p>
<p><em type="italic">Høytlesning fra første stund styrker barnas språkutvikling. Les sammen ofte, helst hver dag! Helt fra barna er ganske små, kan du ha lesestund sammen med barnet ditt. Gjennom kjærlige og trygge relasjoner vil du bidra til at barnets språkferdigheter utvikler seg på en god måte. Noen bøker vil være favoritter, og barnet ditt vil at du skal lese boka om, og om igjen. </em></p>
<p type="title">10 gode grunner til å lese for barnet:</p>
<list><p type="listitem">Det er rolig og koselig å bli lest for!</p>
<p type="listitem">Når vi leser, øker vi ordforråd og språkforståelse hos barnet</p>
<p type="listitem">Dere får en felles opplevelse</p>
<p type="listitem">Dere får mer å snakke om</p>
<p type="listitem">Språket blir bedre</p>
<p type="listitem">Barnet lærer å lytte</p>
<p type="listitem">Dere øker barnets forståelse for andre mennesker og levemåter</p>
<p type="listitem">Barnet får økt selvforståelse ved å gjenkjenne seg selv og andre i bøkene</p>
<p type="listitem">Høytlesing stimulerer fantasi, følelser, lek og drømmer hos barnet</p>
<p type="listitem">Kunnskapen økes – barnet lærer mer</p>
</list><p type="title">Involver familien!</p>
<p>Oppmuntre eldre søsken, besteforeldre og andre voksne også å lese for den lille. Det er en fin måte å styrke felleskap på. Det er å skape lesende rollemodeller og vise at også du og andre voksne har glede av å lese.</p>
<p>Storfamilie i sofa</p>
</body></document>
